tona/__init__.py
tona/cmd/__init__.py
tona/cmd/main.py
tona/models/__init__.py
tona/models/base.py
tona/models/habit.py
tona/models/habit_checkin.py
tona/models/objective.py
tona/models/objective_keyresult.py
tona/models/objective_keyresult_checkin.py
tona/models/project.py
tona/models/project_task.py
tona/models/time_entry.py
tona/utils/__init__.py
tona/utils/dt.py
tona/utils/utils.py
tona/web/__init__.py
tona/web/main.py
tona/web/controllers/__init__.py
tona/web/controllers/habit.py
tona/web/controllers/objective.py
tona/web/controllers/project.py
tona/web/controllers/time_entry.py
tona/web/static/css/bulma.min.css
tona/web/static/js/habit.js
tona/web/static/js/objective.js
tona/web/static/js/project.js
tona/web/static/js/time_entry.js
tona/web/static/js/tona.js
tona/web/templates/base.html
tona/web/templates/habit.html
tona/web/templates/index.html
tona/web/templates/objective.html
tona/web/templates/project.html
tona/web/templates/timer.html
tona-0.1.0.dist-info/LICENSE
tona-0.1.0.dist-info/METADATA
tona-0.1.0.dist-info/WHEEL
tona-0.1.0.dist-info/entry_points.txt
tona-0.1.0.dist-info/top_level.txt
tona-0.1.0.dist-info/RECORD
